odoo/addons/pos_category_complete_name/README.rst
odoo/addons/pos_category_complete_name/__init__.py
odoo/addons/pos_category_complete_name/__manifest__.py
odoo/addons/pos_category_complete_name/i18n/fr.po
odoo/addons/pos_category_complete_name/i18n/it.po
odoo/addons/pos_category_complete_name/i18n/pos_category_complete_name.pot
odoo/addons/pos_category_complete_name/models/__init__.py
odoo/addons/pos_category_complete_name/models/pos_category.py
odoo/addons/pos_category_complete_name/readme/CONTRIBUTORS.rst
odoo/addons/pos_category_complete_name/readme/DESCRIPTION.rst
odoo/addons/pos_category_complete_name/static/description/icon.png
odoo/addons/pos_category_complete_name/static/description/index.html
odoo/addons/pos_category_complete_name/tests/__init__.py
odoo/addons/pos_category_complete_name/tests/test_pos_category_complete_name.py
odoo_addon_pos_category_complete_name-16.0.1.0.0.5.dist-info/METADATA
odoo_addon_pos_category_complete_name-16.0.1.0.0.5.dist-info/WHEEL
odoo_addon_pos_category_complete_name-16.0.1.0.0.5.dist-info/top_level.txt
odoo_addon_pos_category_complete_name-16.0.1.0.0.5.dist-info/RECORD
